.gitignore
.gitmodules
AUTHORS.rst
CONTRIBUTING.rst
HISTORY.rst
MANIFEST.in
Makefile
README.rst
flake.lock
flake.nix
setup.py
tox.ini
version.txt
.github/FUNDING.yml
.github/dependabot.yml
.github/workflows/tests.yml
docs/Makefile
docs/api.rst
docs/conf.py
docs/contributing.rst
docs/history.rst
docs/index.rst
docs/installation.rst
docs/license.rst
docs/usage.rst
docs/_static/snimpy.svg
docs/_themes/.gitignore
docs/_themes/LICENSE
docs/_themes/README
docs/_themes/flask_theme_support.py
docs/_themes/flask/layout.html
docs/_themes/flask/relations.html
docs/_themes/flask/theme.conf
docs/_themes/flask/static/flasky.css_t
docs/_themes/flask_small/layout.html
docs/_themes/flask_small/theme.conf
docs/_themes/flask_small/static/flasky.css_t
examples/add-vlan.py
examples/disable-port-ingress-filtering.py
examples/enable-lldp.py
examples/get-serial.py
examples/list-interfaces.py
examples/list-routes.py
examples/rename-vlan.py
examples/set-syslog-ntp.py
examples/vlan-and-interfaces.py
man/snimpy.1
snimpy/__init__.py
snimpy/__main__.py
snimpy/_version.py
snimpy/basictypes.py
snimpy/config.py
snimpy/main.py
snimpy/manager.py
snimpy/mib.py
snimpy/smi_build.py
snimpy/snmp.py
snimpy.egg-info/PKG-INFO
snimpy.egg-info/SOURCES.txt
snimpy.egg-info/dependency_links.txt
snimpy.egg-info/entry_points.txt
snimpy.egg-info/not-zip-safe
snimpy.egg-info/requires.txt
snimpy.egg-info/top_level.txt
tests/SNIMPY-INVALID-MIB.mib
tests/SNIMPY-MIB.mib
tests/agent.py
tests/test_basictypes.py
tests/test_conf.py
tests/test_main.py
tests/test_manager.py
tests/test_mib.py
tests/test_snmp.py