Metadata-Version: 2.1
Name: snimpy
Version: 1.0.2
Summary: interactive SNMP tool
Home-page: https://github.com/vincentbernat/snimpy
Author: Vincent Bernat
Author-email: bernat@luffy.cx
Classifier: Development Status :: 4 - Beta
Classifier: Environment :: Console
Classifier: Intended Audience :: System Administrators
Classifier: License :: OSI Approved :: ISC License (ISCL)
Classifier: Operating System :: POSIX
Classifier: Programming Language :: Python :: 3
Classifier: Topic :: System :: Networking
Classifier: Topic :: Utilities
Classifier: Topic :: System :: Monitoring
License-File: AUTHORS.rst
